bsdf.py
bsdf_cli.py
bsdf-2.1.1.dist-info/DESCRIPTION.rst
bsdf-2.1.1.dist-info/METADATA
bsdf-2.1.1.dist-info/RECORD
bsdf-2.1.1.dist-info/WHEEL
bsdf-2.1.1.dist-info/entry_points.txt
bsdf-2.1.1.dist-info/metadata.json
bsdf-2.1.1.dist-info/top_level.txt
