Metadata-Version: 2.0
Name: bsdf
Version: 2.1.1
Summary: Python implementation of the Binary Structured Data Format (BSDF).
Home-page: http://bsdf.io
Author: Almar Klein
Author-email: almar.klein@gmail.com
License: UNKNOWN
Platform: UNKNOWN
